[{
  "_id": {
    "$oid": "60d21b4667d0d8992e610ca7"
  },
  "orderId": {
    "$oid": "60d21b4667d0d8992e610c8f"
  },
  "userId": {
    "$oid": "60d21b4667d0d8992e610c88"
  },
  "amount": 799.99,
  "method": "PayOS",
  "status": "paid",
  "paidAt": {
    "$date": "2023-06-24T14:35:00.000Z"
  },
  "createdAt": {
    "$date": "2023-06-24T14:30:00.000Z"
  },
  "updatedAt": {
    "$date": "2023-06-24T14:35:00.000Z"
  }
},
{
  "_id": {
    "$oid": "60d21b4667d0d8992e610ca8"
  },
  "orderId": {
    "$oid": "60d21b4667d0d8992e610ca5"
  },
  "userId": {
    "$oid": "60d21b4667d0d8992e610c88"
  },
  "amount": 49.99,
  "method": "PayOS",
  "status": "paid",
  "createdAt": {
    "$date": "2023-06-26T16:45:00.000Z"
  },
  "updatedAt": {
    "$date": "2025-07-16T17:18:25.670Z"
  },
  "paidAt": {
    "$date": "2025-07-16T17:18:25.665Z"
  }
},
{
  "_id": {
    "$oid": "6877e0b25216b9c2e347372a"
  },
  "orderId": {
    "$oid": "6877e0ac5216b9c2e347371f"
  },
  "userId": {
    "$oid": "60d21b4667d0d8992e610c88"
  },
  "amount": 799.99,
  "method": "COD",
  "status": "paid",
  "createdAt": {
    "$date": "2025-07-16T17:26:10.327Z"
  },
  "updatedAt": {
    "$date": "2025-07-16T17:26:42.038Z"
  },
  "__v": 0,
  "paidAt": {
    "$date": "2025-07-16T17:26:42.038Z"
  }
},
{
  "_id": {
    "$oid": "6877e16a5216b9c2e3473833"
  },
  "orderId": {
    "$oid": "6877e1665216b9c2e3473828"
  },
  "userId": {
    "$oid": "60d21b4667d0d8992e610c88"
  },
  "amount": 799.99,
  "method": "COD",
  "status": "paid",
  "createdAt": {
    "$date": "2025-07-16T17:29:14.907Z"
  },
  "updatedAt": {
    "$date": "2025-07-16T17:30:32.300Z"
  },
  "__v": 0,
  "paidAt": {
    "$date": "2025-07-16T17:30:32.300Z"
  }
},
{
  "_id": {
    "$oid": "6877e4060bd063264e9e2785"
  },
  "orderId": {
    "$oid": "6877e4020bd063264e9e277a"
  },
  "userId": {
    "$oid": "60d21b4667d0d8992e610c88"
  },
  "amount": 799.99,
  "method": "COD",
  "status": "paid",
  "createdAt": {
    "$date": "2025-07-16T17:40:22.886Z"
  },
  "updatedAt": {
    "$date": "2025-07-17T04:09:57.315Z"
  },
  "__v": 0,
  "paidAt": {
    "$date": "2025-07-17T04:09:57.312Z"
  }
},
{
  "_id": {
    "$oid": "6877f5860bd063264e9e2ab4"
  },
  "orderId": {
    "$oid": "6877f5790bd063264e9e2aa9"
  },
  "userId": {
    "$oid": "60d21b4667d0d8992e610c88"
  },
  "amount": 799.99,
  "method": "COD",
  "status": "pending",
  "createdAt": {
    "$date": "2025-07-16T18:55:02.938Z"
  },
  "updatedAt": {
    "$date": "2025-07-16T18:55:02.938Z"
  },
  "__v": 0
},
{
  "_id": {
    "$oid": "6878749b123a66598d7a56e7"
  },
  "orderId": {
    "$oid": "6878748f123a66598d7a56dd"
  },
  "userId": {
    "$oid": "60d21b4667d0d8992e610c88"
  },
  "amount": 1599.98,
  "method": "VietQR",
  "status": "paid",
  "createdAt": {
    "$date": "2025-07-17T03:57:15.055Z"
  },
  "updatedAt": {
    "$date": "2025-07-17T04:36:14.211Z"
  },
  "__v": 0,
  "paidAt": {
    "$date": "2025-07-17T04:36:14.211Z"
  }
},
{
  "_id": {
    "$oid": "687879127f3707c13e424a07"
  },
  "orderId": {
    "$oid": "687878f37f3707c13e4249f8"
  },
  "userId": {
    "$oid": "60d21b4667d0d8992e610c88"
  },
  "amount": 799.99,
  "method": "PayOS",
  "status": "paid",
  "createdAt": {
    "$date": "2025-07-17T04:16:18.277Z"
  },
  "updatedAt": {
    "$date": "2025-07-17T04:18:09.921Z"
  },
  "__v": 0,
  "paidAt": {
    "$date": "2025-07-17T04:18:09.920Z"
  }
},
{
  "_id": {
    "$oid": "68787bf56b781e1c9fd08e5c"
  },
  "orderId": {
    "$oid": "68787bee6b781e1c9fd08e52"
  },
  "userId": {
    "$oid": "60d21b4667d0d8992e610c88"
  },
  "amount": 799.99,
  "method": "COD",
  "status": "paid",
  "createdAt": {
    "$date": "2025-07-17T04:28:37.720Z"
  },
  "updatedAt": {
    "$date": "2025-07-17T04:41:57.812Z"
  },
  "__v": 0,
  "paidAt": {
    "$date": "2025-07-17T04:41:57.809Z"
  }
},
{
  "_id": {
    "$oid": "68787d9293b4c61f2cf119be"
  },
  "orderId": {
    "$oid": "68787d8d93b4c61f2cf119b4"
  },
  "userId": {
    "$oid": "60d21b4667d0d8992e610c88"
  },
  "amount": 799.99,
  "method": "COD",
  "status": "paid",
  "createdAt": {
    "$date": "2025-07-17T04:35:30.997Z"
  },
  "updatedAt": {
    "$date": "2025-07-17T04:42:47.128Z"
  },
  "__v": 0,
  "paidAt": {
    "$date": "2025-07-17T04:42:47.128Z"
  }
},
{
  "_id": {
    "$oid": "687880a3768512009caf479f"
  },
  "orderId": {
    "$oid": "6878809c768512009caf4795"
  },
  "userId": {
    "$oid": "60d21b4667d0d8992e610c88"
  },
  "amount": 1599.98,
  "method": "COD",
  "status": "paid",
  "createdAt": {
    "$date": "2025-07-17T04:48:35.755Z"
  },
  "updatedAt": {
    "$date": "2025-07-17T04:49:03.019Z"
  },
  "__v": 0,
  "paidAt": {
    "$date": "2025-07-17T04:49:03.018Z"
  }
},
{
  "_id": {
    "$oid": "687880e2768512009caf484d"
  },
  "orderId": {
    "$oid": "687880d9768512009caf4843"
  },
  "userId": {
    "$oid": "60d21b4667d0d8992e610c88"
  },
  "amount": 799.99,
  "method": "VietQR",
  "status": "paid",
  "createdAt": {
    "$date": "2025-07-17T04:49:38.311Z"
  },
  "updatedAt": {
    "$date": "2025-07-17T04:49:54.355Z"
  },
  "__v": 0,
  "paidAt": {
    "$date": "2025-07-17T04:49:54.354Z"
  }
},
{
  "_id": {
    "$oid": "687881d3768512009caf48da"
  },
  "orderId": {
    "$oid": "687881ce768512009caf48d0"
  },
  "userId": {
    "$oid": "60d21b4667d0d8992e610c88"
  },
  "amount": 799.99,
  "method": "COD",
  "status": "paid",
  "createdAt": {
    "$date": "2025-07-17T04:53:39.269Z"
  },
  "updatedAt": {
    "$date": "2025-07-17T04:54:06.534Z"
  },
  "__v": 0,
  "paidAt": {
    "$date": "2025-07-17T04:54:06.533Z"
  }
},
{
  "_id": {
    "$oid": "687883e91a70bae7a54b2b45"
  },
  "orderId": {
    "$oid": "687883cd1a70bae7a54b2b33"
  },
  "userId": {
    "$oid": "60d21b4667d0d8992e610c88"
  },
  "amount": 799.99,
  "method": "VietQR",
  "status": "failed",
  "createdAt": {
    "$date": "2025-07-17T05:02:33.424Z"
  },
  "updatedAt": {
    "$date": "2025-07-17T05:02:34.000Z"
  },
  "__v": 0
},
{
  "_id": {
    "$oid": "687885606d721c5cbd0f37b4"
  },
  "orderId": {
    "$oid": "687884801a70bae7a54b2b6c"
  },
  "userId": {
    "$oid": "60d21b4667d0d8992e610c88"
  },
  "amount": 799.99,
  "method": "VietQR",
  "status": "pending",
  "createdAt": {
    "$date": "2025-07-17T05:08:48.739Z"
  },
  "updatedAt": {
    "$date": "2025-07-17T05:08:48.739Z"
  },
  "__v": 0
},
{
  "_id": {
    "$oid": "6878857a6d721c5cbd0f37db"
  },
  "orderId": {
    "$oid": "687885736d721c5cbd0f37d1"
  },
  "userId": {
    "$oid": "60d21b4667d0d8992e610c88"
  },
  "amount": 799.99,
  "method": "VietQR",
  "status": "pending",
  "createdAt": {
    "$date": "2025-07-17T05:09:14.182Z"
  },
  "updatedAt": {
    "$date": "2025-07-17T05:09:14.182Z"
  },
  "__v": 0
},
{
  "_id": {
    "$oid": "687885bf6d721c5cbd0f3830"
  },
  "orderId": {
    "$oid": "687885b96d721c5cbd0f3826"
  },
  "userId": {
    "$oid": "60d21b4667d0d8992e610c88"
  },
  "amount": 3999.95,
  "method": "VietQR",
  "status": "pending",
  "createdAt": {
    "$date": "2025-07-17T05:10:23.701Z"
  },
  "updatedAt": {
    "$date": "2025-07-17T05:10:23.701Z"
  },
  "__v": 0
},
{
  "_id": {
    "$oid": "6878860b6d721c5cbd0f38af"
  },
  "orderId": {
    "$oid": "687886056d721c5cbd0f38a5"
  },
  "userId": {
    "$oid": "60d21b4667d0d8992e610c88"
  },
  "amount": 5599.93,
  "method": "PayOS",
  "status": "pending",
  "createdAt": {
    "$date": "2025-07-17T05:11:39.568Z"
  },
  "updatedAt": {
    "$date": "2025-07-17T05:11:39.568Z"
  },
  "__v": 0
},
{
  "_id": {
    "$oid": "687890f30c10b058457bea2e"
  },
  "orderId": {
    "$oid": "687890ea0c10b058457bea24"
  },
  "userId": {
    "$oid": "60d21b4667d0d8992e610c88"
  },
  "amount": 799.99,
  "method": "PayOS",
  "status": "paid",
  "createdAt": {
    "$date": "2025-07-17T05:58:11.453Z"
  },
  "updatedAt": {
    "$date": "2025-07-17T05:59:49.273Z"
  },
  "__v": 0,
  "paidAt": {
    "$date": "2025-07-17T05:59:49.272Z"
  }
},
{
  "_id": {
    "$oid": "6878b36059f0d5c38338cac5"
  },
  "orderId": {
    "$oid": "6878b35559f0d5c38338cabb"
  },
  "userId": {
    "$oid": "60d21b4667d0d8992e610c88"
  },
  "amount": 799.99,
  "method": "COD",
  "status": "paid",
  "createdAt": {
    "$date": "2025-07-17T08:25:04.171Z"
  },
  "updatedAt": {
    "$date": "2025-07-17T08:26:03.869Z"
  },
  "__v": 0,
  "paidAt": {
    "$date": "2025-07-17T08:26:03.869Z"
  }
},
{
  "_id": {
    "$oid": "6878c4c9bf464d0b6d7daace"
  },
  "orderId": {
    "$oid": "6878c4bfbf464d0b6d7daac4"
  },
  "userId": {
    "$oid": "60d21b4667d0d8992e610c88"
  },
  "amount": 799.99,
  "method": "VietQR",
  "status": "pending",
  "createdAt": {
    "$date": "2025-07-17T09:39:21.635Z"
  },
  "updatedAt": {
    "$date": "2025-07-17T09:39:21.635Z"
  },
  "__v": 0
},
{
  "_id": {
    "$oid": "6879e3d2db800e232f0c665a"
  },
  "orderId": {
    "$oid": "6879e3c3db800e232f0c6650"
  },
  "userId": {
    "$oid": "60d21b4667d0d8992e610c88"
  },
  "amount": 4799.9400000000005,
  "method": "PayOS",
  "status": "pending",
  "createdAt": {
    "$date": "2025-07-18T06:04:02.062Z"
  },
  "updatedAt": {
    "$date": "2025-07-18T06:04:02.062Z"
  },
  "__v": 0
},
{
  "_id": {
    "$oid": "6879e572d5af6ecabee78e94"
  },
  "orderId": {
    "$oid": "6879e56bd5af6ecabee78e84"
  },
  "userId": {
    "$oid": "60d21b4667d0d8992e610c88"
  },
  "amount": 7199.91,
  "method": "VietQR",
  "status": "pending",
  "createdAt": {
    "$date": "2025-07-18T06:10:58.756Z"
  },
  "updatedAt": {
    "$date": "2025-07-18T06:10:58.756Z"
  },
  "__v": 0
},
{
  "_id": {
    "$oid": "6879e60fd5af6ecabee78f68"
  },
  "orderId": {
    "$oid": "6879e5e6d5af6ecabee78f34"
  },
  "userId": {
    "$oid": "60d21b4667d0d8992e610c88"
  },
  "amount": 4799.9400000000005,
  "method": "PayOS",
  "status": "pending",
  "createdAt": {
    "$date": "2025-07-18T06:13:35.416Z"
  },
  "updatedAt": {
    "$date": "2025-07-18T06:13:35.416Z"
  },
  "__v": 0
},
{
  "_id": {
    "$oid": "6879e6dcd5af6ecabee790e6"
  },
  "orderId": {
    "$oid": "6879e6d2d5af6ecabee790d2"
  },
  "userId": {
    "$oid": "60d21b4667d0d8992e610c88"
  },
  "amount": 3199.96,
  "method": "VietQR",
  "status": "paid",
  "createdAt": {
    "$date": "2025-07-18T06:17:00.169Z"
  },
  "updatedAt": {
    "$date": "2025-07-18T06:25:44.336Z"
  },
  "__v": 0,
  "paidAt": {
    "$date": "2025-07-18T06:25:44.336Z"
  }
},
{
  "_id": {
    "$oid": "687fbdde9aac43a05ccbc674"
  },
  "orderId": {
    "$oid": "687fbdd69aac43a05ccbc66a"
  },
  "userId": {
    "$oid": "60d21b4667d0d8992e610c88"
  },
  "amount": 799.99,
  "method": "PayOS",
  "status": "pending",
  "createdAt": {
    "$date": "2025-07-22T16:35:42.366Z"
  },
  "updatedAt": {
    "$date": "2025-07-22T16:35:42.366Z"
  },
  "__v": 0
},
{
  "_id": {
    "$oid": "687fbe2a9aac43a05ccbc703"
  },
  "orderId": {
    "$oid": "687fbe259aac43a05ccbc6f7"
  },
  "userId": {
    "$oid": "60d21b4667d0d8992e610c88"
  },
  "amount": 5599.93,
  "method": "PayOS",
  "status": "pending",
  "createdAt": {
    "$date": "2025-07-22T16:36:58.934Z"
  },
  "updatedAt": {
    "$date": "2025-07-22T16:36:58.934Z"
  },
  "__v": 0
},
{
  "_id": {
    "$oid": "687fbee09c7988f81e309cfa"
  },
  "orderId": {
    "$oid": "687fbeda9c7988f81e309cef"
  },
  "userId": {
    "$oid": "60d21b4667d0d8992e610c88"
  },
  "amount": 4799.9400000000005,
  "method": "PayOS",
  "status": "pending",
  "createdAt": {
    "$date": "2025-07-22T16:40:00.302Z"
  },
  "updatedAt": {
    "$date": "2025-07-22T16:40:00.302Z"
  },
  "__v": 0
},
{
  "_id": {
    "$oid": "687fc145fa897955871cafd3"
  },
  "orderId": {
    "$oid": "687fc140fa897955871cafc9"
  },
  "userId": {
    "$oid": "60d21b4667d0d8992e610c88"
  },
  "amount": 5599.93,
  "method": "PayOS",
  "status": "paid",
  "createdAt": {
    "$date": "2025-07-22T16:50:13.653Z"
  },
  "updatedAt": {
    "$date": "2025-07-22T16:50:32.672Z"
  },
  "__v": 0,
  "transactionId": "1753203013691",
  "paidAt": {
    "$date": "2025-07-22T16:50:32.672Z"
  }
},
{
  "_id": {
    "$oid": "687fc67084e62469b68d1750"
  },
  "orderId": {
    "$oid": "687fc66984e62469b68d1746"
  },
  "userId": {
    "$oid": "60d21b4667d0d8992e610c88"
  },
  "amount": 6399.92,
  "method": "PayOS",
  "status": "paid",
  "createdAt": {
    "$date": "2025-07-22T17:12:16.167Z"
  },
  "updatedAt": {
    "$date": "2025-07-22T17:12:38.558Z"
  },
  "__v": 0,
  "transactionId": "1753204336170",
  "paidAt": {
    "$date": "2025-07-22T17:12:38.558Z"
  }
},
{
  "_id": {
    "$oid": "687fcc763206e9147a0ffa08"
  },
  "orderId": {
    "$oid": "687fcc743206e9147a0ff9fe"
  },
  "userId": {
    "$oid": "60d21b4667d0d8992e610c88"
  },
  "amount": 3199.96,
  "method": "PayOS",
  "status": "paid",
  "createdAt": {
    "$date": "2025-07-22T17:37:58.829Z"
  },
  "updatedAt": {
    "$date": "2025-07-22T17:40:00.248Z"
  },
  "__v": 0,
  "transactionId": "1753205878832",
  "paidAt": {
    "$date": "2025-07-22T17:40:00.247Z"
  }
},
{
  "_id": {
    "$oid": "687fccde95a72f0838f53ba2"
  },
  "orderId": {
    "$oid": "687fccd795a72f0838f53b98"
  },
  "userId": {
    "$oid": "60d21b4667d0d8992e610c88"
  },
  "amount": 2599.98,
  "method": "PayOS",
  "status": "paid",
  "createdAt": {
    "$date": "2025-07-22T17:39:42.360Z"
  },
  "updatedAt": {
    "$date": "2025-07-22T17:39:59.318Z"
  },
  "__v": 0,
  "transactionId": "1753205982362",
  "paidAt": {
    "$date": "2025-07-22T17:39:59.318Z"
  }
},
{
  "_id": {
    "$oid": "68800e8712519642912aeefa"
  },
  "orderId": {
    "$oid": "68800e8112519642912aeef0"
  },
  "userId": {
    "$oid": "60d21b4667d0d8992e610c88"
  },
  "amount": 2599.98,
  "method": "PayOS",
  "status": "paid",
  "createdAt": {
    "$date": "2025-07-22T22:19:51.247Z"
  },
  "updatedAt": {
    "$date": "2025-07-22T22:20:38.466Z"
  },
  "__v": 0,
  "transactionId": "1753222791274",
  "paidAt": {
    "$date": "2025-07-22T22:20:38.466Z"
  }
},
{
  "_id": {
    "$oid": "688051f9b2338f453606b96a"
  },
  "orderId": {
    "$oid": "688051f3b2338f453606b960"
  },
  "userId": {
    "$oid": "60d21b4667d0d8992e610c88"
  },
  "amount": 2599.98,
  "method": "PayOS",
  "status": "paid",
  "createdAt": {
    "$date": "2025-07-23T03:07:37.991Z"
  },
  "updatedAt": {
    "$date": "2025-07-23T03:07:57.532Z"
  },
  "__v": 0,
  "transactionId": "1753240057996",
  "paidAt": {
    "$date": "2025-07-23T03:07:57.531Z"
  }
},
{
  "_id": {
    "$oid": "688056b7b2338f453606e157"
  },
  "orderId": {
    "$oid": "688056b0b2338f453606e14d"
  },
  "userId": {
    "$oid": "60d21b4667d0d8992e610c88"
  },
  "amount": 2599.98,
  "method": "COD",
  "status": "paid",
  "createdAt": {
    "$date": "2025-07-23T03:27:51.054Z"
  },
  "updatedAt": {
    "$date": "2025-07-23T03:28:10.945Z"
  },
  "__v": 0,
  "paidAt": {
    "$date": "2025-07-23T03:28:10.944Z"
  }
},
{
  "_id": {
    "$oid": "688059ceb2338f453606e3d8"
  },
  "orderId": {
    "$oid": "688059c6b2338f453606e3ce"
  },
  "userId": {
    "$oid": "60d21b4667d0d8992e610c88"
  },
  "amount": 2599.98,
  "method": "PayOS",
  "status": "paid",
  "createdAt": {
    "$date": "2025-07-23T03:41:02.714Z"
  },
  "updatedAt": {
    "$date": "2025-07-23T03:41:24.025Z"
  },
  "__v": 0,
  "transactionId": "1753242062718",
  "paidAt": {
    "$date": "2025-07-23T03:41:24.024Z"
  }
},
{
  "_id": {
    "$oid": "688104151a1be0d59d27157e"
  },
  "orderId": {
    "$oid": "6881040e1a1be0d59d271574"
  },
  "userId": {
    "$oid": "60d21b4667d0d8992e610c88"
  },
  "amount": 2599.98,
  "method": "PayOS",
  "status": "paid",
  "createdAt": {
    "$date": "2025-07-23T15:47:33.669Z"
  },
  "updatedAt": {
    "$date": "2025-07-23T15:47:50.716Z"
  },
  "__v": 0,
  "transactionId": "1753285653703",
  "paidAt": {
    "$date": "2025-07-23T15:47:50.716Z"
  }
},
{
  "_id": {
    "$oid": "688107171a1be0d59d2718e1"
  },
  "orderId": {
    "$oid": "688107121a1be0d59d2718d7"
  },
  "userId": {
    "$oid": "60d21b4667d0d8992e610c88"
  },
  "amount": 2599.98,
  "method": "PayOS",
  "status": "paid",
  "createdAt": {
    "$date": "2025-07-23T16:00:23.688Z"
  },
  "updatedAt": {
    "$date": "2025-07-23T16:00:44.765Z"
  },
  "__v": 0,
  "transactionId": "1753286423689",
  "paidAt": {
    "$date": "2025-07-23T16:00:44.765Z"
  }
},
{
  "_id": {
    "$oid": "68810acc8e0307c89ddcb043"
  },
  "orderId": {
    "$oid": "68810ac78e0307c89ddcb038"
  },
  "userId": {
    "$oid": "60d21b4667d0d8992e610c88"
  },
  "amount": 2599.98,
  "method": "VietQR",
  "status": "pending",
  "createdAt": {
    "$date": "2025-07-23T16:16:12.927Z"
  },
  "updatedAt": {
    "$date": "2025-07-23T16:16:12.930Z"
  },
  "__v": 0,
  "transactionId": "68810ac78e0307c89ddcb038"
},
{
  "_id": {
    "$oid": "68810b1e8e0307c89ddcb0a4"
  },
  "orderId": {
    "$oid": "68810b198e0307c89ddcb099"
  },
  "userId": {
    "$oid": "60d21b4667d0d8992e610c88"
  },
  "amount": 2599.98,
  "method": "PayOS",
  "status": "paid",
  "createdAt": {
    "$date": "2025-07-23T16:17:34.832Z"
  },
  "updatedAt": {
    "$date": "2025-07-23T16:17:53.690Z"
  },
  "__v": 0,
  "transactionId": "1753287454834",
  "paidAt": {
    "$date": "2025-07-23T16:17:53.690Z"
  }
},
{
  "_id": {
    "$oid": "688113a9214f12ef68db6546"
  },
  "orderId": {
    "$oid": "688113a2214f12ef68db6539"
  },
  "userId": {
    "$oid": "60d21b4667d0d8992e610c88"
  },
  "amount": 4199.96,
  "method": "PayOS",
  "status": "paid",
  "createdAt": {
    "$date": "2025-07-23T16:54:01.708Z"
  },
  "updatedAt": {
    "$date": "2025-07-23T16:54:20.689Z"
  },
  "__v": 0,
  "transactionId": "1753289641710",
  "paidAt": {
    "$date": "2025-07-23T16:54:20.688Z"
  }
},
{
  "_id": {
    "$oid": "6881159d9ced608a009cbd83"
  },
  "orderId": {
    "$oid": "688115949ced608a009cbd79"
  },
  "userId": {
    "$oid": "60d21b4667d0d8992e610c88"
  },
  "amount": 2599.98,
  "method": "COD",
  "status": "pending",
  "createdAt": {
    "$date": "2025-07-23T17:02:21.221Z"
  },
  "updatedAt": {
    "$date": "2025-07-23T17:02:21.221Z"
  },
  "__v": 0
},
{
  "_id": {
    "$oid": "68811a339ced608a009cc12a"
  },
  "orderId": {
    "$oid": "68811a189ced608a009cc11d"
  },
  "userId": {
    "$oid": "60d21b4667d0d8992e610c88"
  },
  "amount": 3399.9700000000003,
  "method": "COD",
  "status": "paid",
  "createdAt": {
    "$date": "2025-07-23T17:21:55.381Z"
  },
  "updatedAt": {
    "$date": "2025-07-23T17:23:57.750Z"
  },
  "__v": 0,
  "paidAt": {
    "$date": "2025-07-23T17:23:57.749Z"
  }
},
{
  "_id": {
    "$oid": "6881ac3ac63354632aa9c207"
  },
  "orderId": {
    "$oid": "6881ac34c63354632aa9c1fd"
  },
  "userId": {
    "$oid": "60d21b4667d0d8992e610c88"
  },
  "amount": 799.99,
  "method": "COD",
  "status": "pending",
  "createdAt": {
    "$date": "2025-07-24T03:44:58.421Z"
  },
  "updatedAt": {
    "$date": "2025-07-24T03:44:58.421Z"
  },
  "__v": 0
},
{
  "_id": {
    "$oid": "6881af5824e3fa498a81f5b3"
  },
  "orderId": {
    "$oid": "68811256e3186dad2cc58c0c"
  },
  "userId": {
    "$oid": "60d21b4667d0d8992e610c88"
  },
  "amount": 4699.96,
  "method": "PayOS",
  "status": "pending",
  "createdAt": {
    "$date": "2025-07-24T03:58:16.641Z"
  },
  "updatedAt": {
    "$date": "2025-07-24T03:58:16.652Z"
  },
  "__v": 0,
  "transactionId": "1753329496649"
},
{
  "_id": {
    "$oid": "6881b188ef0808a5548722aa"
  },
  "orderId": {
    "$oid": "6881b09124e3fa498a81f91d"
  },
  "userId": {
    "$oid": "60d21b4667d0d8992e610c88"
  },
  "amount": 3899.9700000000003,
  "method": "PayOS",
  "status": "paid",
  "createdAt": {
    "$date": "2025-07-24T04:07:36.573Z"
  },
  "updatedAt": {
    "$date": "2025-07-24T04:08:14.695Z"
  },
  "__v": 0,
  "transactionId": "1753330056576",
  "paidAt": {
    "$date": "2025-07-24T04:08:14.694Z"
  }
},
{
  "_id": {
    "$oid": "6881b2deef0808a5548728f3"
  },
  "orderId": {
    "$oid": "6881b2d6ef0808a5548728e9"
  },
  "userId": {
    "$oid": "60d21b4667d0d8992e610c88"
  },
  "amount": 2599.98,
  "method": "PayOS",
  "status": "paid",
  "createdAt": {
    "$date": "2025-07-24T04:13:18.305Z"
  },
  "updatedAt": {
    "$date": "2025-07-24T04:13:34.682Z"
  },
  "__v": 0,
  "transactionId": "1753330398307",
  "paidAt": {
    "$date": "2025-07-24T04:13:34.682Z"
  }
}]